LICENSE
rawfinder/__init__.py
rawfinder/app.py
rawfinder/cli.py
rawfinder/config.py
rawfinder/copier.py
rawfinder/exceptions.py
rawfinder/finder.py
rawfinder/gui/__init__.py
rawfinder/integrity.py
rawfinder/logging.py
rawfinder/matcher.py
rawfinder/reporters/__init__.py
rawfinder/reporters/factories.py
rawfinder/reporters/plain.py
rawfinder/reporters/rich.py
rawfinder-0.3.3.dist-info/LICENSE
rawfinder-0.3.3.dist-info/METADATA
rawfinder-0.3.3.dist-info/WHEEL
rawfinder-0.3.3.dist-info/entry_points.txt
rawfinder-0.3.3.dist-info/RECORD
