Metadata-Version: 2.1
Name: rawfinder
Version: 0.3.3
Summary: CLI tool to organize RAW photos by matching JPEG counterparts
Home-page: https://github.com/moskrc/rawfinder
Keywords: photography,raw,organizer,cli,fuji,canon,sony,nikon,ricoh,pentax,olympus
Author: Vitalii Shishorin
Author-email: moskrc@gmail.com
Requires-Python: >=3.9,<4.0
Classifier: Programming Language :: Python :: 3
Classifier: Programming Language :: Python :: 3.9
Classifier: Programming Language :: Python :: 3.10
Classifier: Programming Language :: Python :: 3.11
Classifier: Programming Language :: Python :: 3.12
Requires-Dist: appdirs (>=1.4.4,<2.0.0)
Requires-Dist: click (>=8.1.8,<9.0.0)
Requires-Dist: pydantic (>=2.10.6,<3.0.0)
Requires-Dist: pyyaml (>=6.0.1,<7.0.0)
Requires-Dist: rich (>=13.9.4,<14.0.0)
Project-URL: Documentation, https://moskrc.github.io/rawfinder/
Project-URL: Repository, https://github.com/moskrc/rawfinder
